[{"date":"2026-01-22","open":190100.0,"high":201000.0,"low":190000.0,"close":194400.0,"volume":18257.0,"ma5":null,"ma20":null,"ma60":null,"bb_upper":null,"bb_lower":null,"vwap":null,"rsi":50.0,"macd_hist":0.0},{"date":"2026-01-23","open":192000.0,"high":198400.0,"low":192000.0,"close":196200.0,"volume":17988.0,"ma5":null,"ma20":null,"ma60":null,"bb_upper":null,"bb_lower":null,"vwap":null,"rsi":50.0,"macd_hist":114.9},{"date":"2026-01-26","open":191300.0,"high":196000.0,"low":186500.0,"close":190900.0,"volume":17429.0,"ma5":null,"ma20":null,"ma60":null,"bb_upper":null,"bb_lower":null,"vwap":null,"rsi":81.5,"macd_hist":-157.6},{"date":"2026-01-27","open":192900.0,"high":194500.0,"low":185600.0,"close":191700.0,"volume":15248.0,"ma5":null,"ma20":null,"ma60":null,"bb_upper":null,"bb_lower":null,"vwap":null,"rsi":82.1,"macd_hist":-269.0},{"date":"2026-01-28","open":192000.0,"high":199000.0,"low":191700.0,"close":196900.0,"volume":13001.0,"ma5":194020.0,"ma20":null,"ma60":null,"bb_upper":null,"bb_lower":null,"vwap":null,"rsi":85.1,"macd_hist":7.8},{"date":"2026-01-29","open":200500.0,"high":205000.0,"low":193200.0,"close":201500.0,"volume":20540.0,"ma5":195440.0,"ma20":null,"ma60":null,"bb_upper":null,"bb_lower":null,"vwap":null,"rsi":87.2,"macd_hist":475.2},{"date":"2026-01-30","open":197600.0,"high":210500.0,"low":197600.0,"close":207000.0,"volume":20753.0,"ma5":197600.0,"ma20":null,"ma60":null,"bb_upper":null,"bb_lower":null,"vwap":null,"rsi":89.1,"macd_hist":1093.8},{"date":"2026-02-02","open":209500.0,"high":209500.0,"low":198700.0,"close":202000.0,"volume":20094.0,"ma5":199820.0,"ma20":null,"ma60":null,"bb_upper":null,"bb_lower":null,"vwap":null,"rsi":77.6,"macd_hist":1102.2},{"date":"2026-02-03","open":215000.0,"high":215000.0,"low":204000.0,"close":208500.0,"volume":13563.0,"ma5":203180.0,"ma20":null,"ma60":null,"bb_upper":null,"bb_lower":null,"vwap":null,"rsi":81.0,"macd_hist":1459.2},{"date":"2026-02-04","open":208500.0,"high":215000.0,"low":202000.0,"close":212500.0,"volume":12731.0,"ma5":206300.0,"ma20":null,"ma60":null,"bb_upper":null,"bb_lower":null,"vwap":null,"rsi":82.8,"macd_hist":1852.9},{"date":"2026-02-05","open":206000.0,"high":222000.0,"low":202000.0,"close":217500.0,"volume":33516.0,"ma5":209500.0,"ma20":null,"ma60":null,"bb_upper":null,"bb_lower":null,"vwap":null,"rsi":84.7,"macd_hist":2308.8},{"date":"2026-02-06","open":206500.0,"high":214000.0,"low":200500.0,"close":207500.0,"volume":14580.0,"ma5":209600.0,"ma20":null,"ma60":null,"bb_upper":null,"bb_lower":null,"vwap":null,"rsi":68.4,"macd_hist":1817.0},{"date":"2026-02-09","open":222000.0,"high":223000.0,"low":209000.0,"close":215000.0,"volume":24822.0,"ma5":212200.0,"ma20":null,"ma60":null,"bb_upper":null,"bb_lower":null,"vwap":null,"rsi":72.7,"macd_hist":1869.9},{"date":"2026-02-10","open":220000.0,"high":228000.0,"low":215000.0,"close":227500.0,"volume":19403.0,"ma5":216000.0,"ma20":null,"ma60":null,"bb_upper":null,"bb_lower":null,"vwap":null,"rsi":78.0,"macd_hist":2576.1},{"date":"2026-02-11","open":233500.0,"high":234000.0,"low":222000.0,"close":227000.0,"volume":18023.0,"ma5":218900.0,"ma20":null,"ma60":null,"bb_upper":null,"bb_lower":null,"vwap":null,"rsi":77.3,"macd_hist":2819.3},{"date":"2026-02-12","open":225000.0,"high":243500.0,"low":225000.0,"close":242000.0,"volume":25121.0,"ma5":223800.0,"ma20":null,"ma60":null,"bb_upper":null,"bb_lower":null,"vwap":null,"rsi":82.1,"macd_hist":3742.3},{"date":"2026-02-13","open":238000.0,"high":240000.0,"low":228000.0,"close":233000.0,"volume":20342.0,"ma5":228900.0,"ma20":null,"ma60":null,"bb_upper":null,"bb_lower":null,"vwap":null,"rsi":72.2,"macd_hist":3502.8},{"date":"2026-02-19","open":233000.0,"high":236000.0,"low":222000.0,"close":223000.0,"volume":31490.0,"ma5":230500.0,"ma20":null,"ma60":null,"bb_upper":null,"bb_lower":null,"vwap":null,"rsi":63.2,"macd_hist":2475.5},{"date":"2026-02-20","open":220500.0,"high":229500.0,"low":220500.0,"close":225500.0,"volume":14823.0,"ma5":230100.0,"ma20":null,"ma60":null,"bb_upper":null,"bb_lower":null,"vwap":null,"rsi":64.4,"macd_hist":1800.3},{"date":"2026-02-23","open":223500.0,"high":236500.0,"low":220000.0,"close":230500.0,"volume":20234.0,"ma5":230800.0,"ma20":212505.0,"ma60":null,"bb_upper":242935.63,"bb_lower":182074.37,"vwap":213352.65,"rsi":66.7,"macd_hist":1536.7},{"date":"2026-02-24","open":238000.0,"high":238500.0,"low":227000.0,"close":231500.0,"volume":24804.0,"ma5":228700.0,"ma20":214360.0,"ma60":null,"bb_upper":244666.53,"bb_lower":184053.47,"vwap":215368.75,"rsi":67.2,"macd_hist":1286.0},{"date":"2026-02-25","open":229000.0,"high":253000.0,"low":228500.0,"close":250000.0,"volume":28530.0,"ma5":232100.0,"ma20":217050.0,"ma60":null,"bb_upper":250004.55,"bb_lower":184095.45,"vwap":218226.35,"rsi":74.3,"macd_hist":2170.5},{"date":"2026-02-26","open":247500.0,"high":251000.0,"low":241500.0,"close":245000.0,"volume":18187.0,"ma5":236500.0,"ma20":219755.0,"ma60":null,"bb_upper":252552.78,"bb_lower":186957.22,"vwap":220603.81,"rsi":69.9,"macd_hist":2215.5},{"date":"2026-02-27","open":246000.0,"high":262000.0,"low":242000.0,"close":249500.0,"volume":39366.0,"ma5":241300.0,"ma20":222645.0,"ma60":null,"bb_upper":255219.42,"bb_lower":190070.58,"vwap":224430.84,"rsi":71.5,"macd_hist":2333.2},{"date":"2026-03-03","open":247000.0,"high":251500.0,"low":238500.0,"close":244000.0,"volume":25721.0,"ma5":244000.0,"ma20":225000.0,"ma60":null,"bb_upper":256531.1,"bb_lower":193468.9,"vwap":226427.62,"rsi":66.7,"macd_hist":1846.7},{"date":"2026-03-04","open":248500.0,"high":252000.0,"low":212000.0,"close":214000.0,"volume":32272.0,"ma5":240500.0,"ma20":225625.0,"ma60":null,"bb_upper":255654.59,"bb_lower":195595.41,"vwap":227586.23,"rsi":47.9,"macd_hist":-560.7},{"date":"2026-03-05","open":224000.0,"high":235500.0,"low":221000.0,"close":227000.0,"volume":20254.0,"ma5":235900.0,"ma20":226625.0,"ma60":null,"bb_upper":255346.67,"bb_lower":197903.33,"vwap":228619.35,"rsi":53.9,"macd_hist":-1300.4},{"date":"2026-03-06","open":217000.0,"high":234500.0,"low":216500.0,"close":230500.0,"volume":12551.0,"ma5":233000.0,"ma20":228050.0,"ma60":null,"bb_upper":254353.69,"bb_lower":201746.31,"vwap":229704.16,"rsi":55.5,"macd_hist":-1559.4},{"date":"2026-03-09","open":215000.0,"high":227000.0,"low":213000.0,"close":221000.0,"volume":12926.0,"ma5":227300.0,"ma20":228675.0,"ma60":null,"bb_upper":253579.61,"bb_lower":203770.39,"vwap":230054.23,"rsi":50.6,"macd_hist":-2329.6},{"date":"2026-03-10","open":242000.0,"high":242000.0,"low":218000.0,"close":222500.0,"volume":12537.0,"ma5":223000.0,"ma20":229175.0,"ma60":null,"bb_upper":253094.33,"bb_lower":205255.67,"vwap":230555.69,"rsi":51.3,"macd_hist":-2672.5},{"date":"2026-03-11","open":232500.0,"high":238500.0,"low":227000.0,"close":230500.0,"volume":19328.0,"ma5":226300.0,"ma20":229825.0,"ma60":null,"bb_upper":253106.52,"bb_lower":206543.48,"vwap":231907.32,"rsi":55.1,"macd_hist":-2308.7},{"date":"2026-03-12","open":232000.0,"high":239000.0,"low":228500.0,"close":238000.0,"volume":15990.0,"ma5":228500.0,"ma20":231350.0,"ma60":null,"bb_upper":252359.02,"bb_lower":210340.98,"vwap":232847.06,"rsi":58.4,"macd_hist":-1547.7},{"date":"2026-03-13","open":229500.0,"high":235000.0,"low":222000.0,"close":223000.0,"volume":16333.0,"ma5":227000.0,"ma20":231750.0,"ma60":null,"bb_upper":251727.62,"bb_lower":211772.38,"vwap":233607.17,"rsi":50.5,"macd_hist":-2010.0},{"date":"2026-03-16","open":221000.0,"high":229000.0,"low":215500.0,"close":219000.0,"volume":11138.0,"ma5":226600.0,"ma20":231325.0,"ma60":null,"bb_upper":252031.66,"bb_lower":210618.34,"vwap":233744.2,"rsi":48.6,"macd_hist":-2508.2},{"date":"2026-03-17","open":220000.0,"high":229500.0,"low":220000.0,"close":225000.0,"volume":11038.0,"ma5":227100.0,"ma20":231225.0,"ma60":null,"bb_upper":252038.65,"bb_lower":210411.35,"vwap":233771.26,"rsi":51.5,"macd_hist":-2358.9},{"date":"2026-03-18","open":235500.0,"high":239500.0,"low":226000.0,"close":237500.0,"volume":23197.0,"ma5":228500.0,"ma20":231000.0,"ma60":null,"bb_upper":251416.71,"bb_lower":210583.29,"vwap":233615.85,"rsi":57.0,"macd_hist":-1391.4},{"date":"2026-03-19","open":232500.0,"high":232500.0,"low":219000.0,"close":221500.0,"volume":18708.0,"ma5":225200.0,"ma20":230425.0,"ma60":null,"bb_upper":251248.25,"bb_lower":209601.75,"vwap":233189.18,"rsi":49.3,"macd_hist":-1777.5},{"date":"2026-03-20","open":223500.0,"high":235000.0,"low":223500.0,"close":227000.0,"volume":25748.0,"ma5":226000.0,"ma20":230625.0,"ma60":null,"bb_upper":251223.61,"bb_lower":210026.39,"vwap":233372.89,"rsi":51.7,"macd_hist":-1615.5},{"date":"2026-03-23","open":217000.0,"high":224500.0,"low":212000.0,"close":216000.0,"volume":16142.0,"ma5":225400.0,"ma20":230150.0,"ma60":null,"bb_upper":251664.01,"bb_lower":208635.99,"vwap":233040.6,"rsi":46.9,"macd_hist":-2167.8},{"date":"2026-03-24","open":228500.0,"high":229500.0,"low":217000.0,"close":222500.0,"volume":10332.0,"ma5":224900.0,"ma20":229750.0,"ma60":null,"bb_upper":251532.42,"bb_lower":207967.58,"vwap":232984.96,"rsi":49.9,"macd_hist":-2017.2},{"date":"2026-03-25","open":238000.0,"high":238000.0,"low":217500.0,"close":220500.0,"volume":17801.0,"ma5":221500.0,"ma20":229200.0,"ma60":null,"bb_upper":251348.78,"bb_lower":207051.22,"vwap":232675.65,"rsi":49.0,"macd_hist":-1971.7},{"date":"2026-03-26","open":223000.0,"high":225500.0,"low":217000.0,"close":219000.0,"volume":10984.0,"ma5":221000.0,"ma20":227650.0,"ma60":null,"bb_upper":247929.88,"bb_lower":207370.12,"vwap":231455.67,"rsi":48.3,"macd_hist":-1958.0},{"date":"2026-03-27","open":219500.0,"high":224500.0,"low":213500.0,"close":222500.0,"volume":11972.0,"ma5":220100.0,"ma20":226525.0,"ma60":null,"bb_upper":245183.92,"bb_lower":207866.08,"vwap":230367.01,"rsi":50.1,"macd_hist":-1641.5},{"date":"2026-03-30","open":211500.0,"high":227000.0,"low":211500.0,"close":223000.0,"volume":18335.0,"ma5":221500.0,"ma20":225200.0,"ma60":null,"bb_upper":240439.84,"bb_lower":209960.16,"vwap":227455.01,"rsi":50.3,"macd_hist":-1339.5},{"date":"2026-03-31","open":219500.0,"high":226000.0,"low":216000.0,"close":219000.0,"volume":15321.0,"ma5":220800.0,"ma20":223950.0,"ma60":null,"bb_upper":236573.7,"bb_lower":211326.3,"vwap":225797.46,"rsi":48.1,"macd_hist":-1346.6},{"date":"2026-04-01","open":237000.0,"high":237000.0,"low":217000.0,"close":225000.0,"volume":14764.0,"ma5":221700.0,"ma20":224500.0,"ma60":null,"bb_upper":236224.92,"bb_lower":212775.08,"vwap":225801.82,"rsi":51.6,"macd_hist":-905.7},{"date":"2026-04-02","open":225500.0,"high":231500.0,"low":214500.0,"close":216000.0,"volume":13730.0,"ma5":221100.0,"ma20":223950.0,"ma60":null,"bb_upper":236201.32,"bb_lower":211698.68,"vwap":225440.34,"rsi":46.6,"macd_hist":-1162.3},{"date":"2026-04-03","open":219500.0,"high":225000.0,"low":210000.0,"close":210500.0,"volume":10217.0,"ma5":218700.0,"ma20":222950.0,"ma60":null,"bb_upper":236176.37,"bb_lower":209723.63,"vwap":225027.23,"rsi":43.8,"macd_hist":-1616.8},{"date":"2026-04-06","open":210500.0,"high":210500.0,"low":199900.0,"close":203500.0,"volume":26281.0,"ma5":214800.0,"ma20":222075.0,"ma60":null,"bb_upper":237903.94,"bb_lower":206246.06,"vwap":223541.44,"rsi":40.4,"macd_hist":-2263.4},{"date":"2026-04-07","open":200500.0,"high":211500.0,"low":200500.0,"close":205500.0,"volume":8183.0,"ma5":212100.0,"ma20":221225.0,"ma60":null,"bb_upper":238698.21,"bb_lower":203751.79,"vwap":222924.93,"rsi":41.8,"macd_hist":-2417.0},{"date":"2026-04-08","open":230000.0,"high":230500.0,"low":210000.0,"close":215500.0,"volume":21067.0,"ma5":210200.0,"ma20":220475.0,"ma60":null,"bb_upper":237555.23,"bb_lower":203394.77,"vwap":222089.36,"rsi":48.2,"macd_hist":-1737.5},{"date":"2026-04-09","open":216500.0,"high":223500.0,"low":216500.0,"close":223000.0,"volume":17112.0,"ma5":211600.0,"ma20":219725.0,"ma60":null,"bb_upper":234759.96,"bb_lower":204690.04,"vwap":221374.08,"rsi":52.4,"macd_hist":-727.1},{"date":"2026-04-10","open":220500.0,"high":227000.0,"low":213000.0,"close":216500.0,"volume":12296.0,"ma5":212800.0,"ma20":219400.0,"ma60":null,"bb_upper":234417.88,"bb_lower":204382.12,"vwap":220999.72,"rsi":48.7,"macd_hist":-454.0},{"date":"2026-04-13","open":210000.0,"high":216000.0,"low":208000.0,"close":210000.0,"volume":15182.0,"ma5":214100.0,"ma20":218950.0,"ma60":null,"bb_upper":234546.56,"bb_lower":203353.44,"vwap":220532.98,"rsi":45.3,"macd_hist":-656.4},{"date":"2026-04-14","open":211000.0,"high":217500.0,"low":210500.0,"close":214500.0,"volume":20889.0,"ma5":215900.0,"ma20":218425.0,"ma60":null,"bb_upper":233870.23,"bb_lower":202979.77,"vwap":219983.26,"rsi":48.0,"macd_hist":-442.6},{"date":"2026-04-15","open":216500.0,"high":219000.0,"low":208500.0,"close":209000.0,"volume":20486.0,"ma5":214600.0,"ma20":217000.0,"ma60":null,"bb_upper":230118.89,"bb_lower":203881.11,"vwap":218468.87,"rsi":45.0,"macd_hist":-616.3},{"date":"2026-04-16","open":213000.0,"high":219000.0,"low":211000.0,"close":215500.0,"volume":11338.0,"ma5":213100.0,"ma20":216700.0,"ma60":null,"bb_upper":229659.04,"bb_lower":203740.96,"vwap":218006.39,"rsi":49.0,"macd_hist":-256.7},{"date":"2026-04-17","open":213500.0,"high":218000.0,"low":209500.0,"close":211000.0,"volume":14563.0,"ma5":212000.0,"ma20":215900.0,"ma60":null,"bb_upper":228137.13,"bb_lower":203662.87,"vwap":216880.88,"rsi":46.5,"macd_hist":-283.0},{"date":"2026-04-20","open":217500.0,"high":217500.0,"low":209500.0,"close":211000.0,"volume":12376.0,"ma5":212200.0,"ma20":215650.0,"ma60":null,"bb_upper":228081.28,"bb_lower":203218.72,"vwap":216675.92,"rsi":46.5,"macd_hist":-262.0},{"date":"2026-04-21","open":212500.0,"high":216500.0,"low":210500.0,"close":212000.0,"volume":20461.0,"ma5":211700.0,"ma20":215125.0,"ma60":219126.67,"bb_upper":227220.56,"bb_lower":203029.44,"vwap":216227.38,"rsi":47.2,"macd_hist":-148.0},{"date":"2026-04-22","open":211000.0,"high":218000.0,"low":211000.0,"close":212500.0,"volume":11451.0,"ma5":212400.0,"ma20":214725.0,"ma60":219428.33,"bb_upper":226599.23,"bb_lower":202850.77,"vwap":215610.11,"rsi":47.6,"macd_hist":-13.3},{"date":"2026-04-23","open":229500.0,"high":229500.0,"low":213500.0,"close":217000.0,"volume":18004.0,"ma5":212700.0,"ma20":214625.0,"ma60":219775.0,"bb_upper":226380.74,"bb_lower":202869.26,"vwap":215690.75,"rsi":50.9,"macd_hist":382.6},{"date":"2026-04-24","open":221500.0,"high":221500.0,"low":210000.0,"close":211000.0,"volume":17878.0,"ma5":212700.0,"ma20":214050.0,"ma60":220110.0,"bb_upper":225297.92,"bb_lower":202802.08,"vwap":215438.1,"rsi":46.7,"macd_hist":250.6},{"date":"2026-04-27","open":215000.0,"high":217500.0,"low":208000.0,"close":209000.0,"volume":18126.0,"ma5":212300.0,"ma20":213350.0,"ma60":220398.33,"bb_upper":223978.17,"bb_lower":202721.83,"vwap":214924.56,"rsi":45.3,"macd_hist":49.2},{"date":"2026-04-28","open":209000.0,"high":211500.0,"low":206000.0,"close":206000.0,"volume":16611.0,"ma5":211100.0,"ma20":212700.0,"ma60":220550.0,"bb_upper":223462.51,"bb_lower":201937.49,"vwap":214299.47,"rsi":43.3,"macd_hist":-249.0},{"date":"2026-04-29","open":208500.0,"high":213500.0,"low":207000.0,"close":212000.0,"volume":20169.0,"ma5":211000.0,"ma20":212050.0,"ma60":220725.0,"bb_upper":221122.22,"bb_lower":202977.78,"vwap":213541.02,"rsi":48.3,"macd_hist":-17.3},{"date":"2026-04-30","open":209000.0,"high":212000.0,"low":206500.0,"close":208000.0,"volume":13097.0,"ma5":209200.0,"ma20":211650.0,"ma60":220741.67,"bb_upper":220694.34,"bb_lower":202605.66,"vwap":213051.46,"rsi":45.4,"macd_hist":-103.7},{"date":"2026-05-04","open":214000.0,"high":216500.0,"low":209000.0,"close":211500.0,"volume":16165.0,"ma5":209300.0,"ma20":211700.0,"ma60":220900.0,"bb_upper":220728.61,"bb_lower":202671.39,"vwap":212951.32,"rsi":48.3,"macd_hist":93.8},{"date":"2026-05-06","open":209500.0,"high":210500.0,"low":201500.0,"close":203000.0,"volume":26124.0,"ma5":208100.0,"ma20":211675.0,"ma60":220808.33,"bb_upper":220801.45,"bb_lower":202548.55,"vwap":212984.15,"rsi":42.4,"macd_hist":-307.1},{"date":"2026-05-07","open":203500.0,"high":214000.0,"low":203500.0,"close":211500.0,"volume":16682.0,"ma5":209200.0,"ma20":211975.0,"ma60":220791.67,"bb_upper":220629.02,"bb_lower":203320.98,"vwap":212993.48,"rsi":49.1,"macd_hist":23.6},{"date":"2026-05-08","open":219500.0,"high":219500.0,"low":206500.0,"close":209000.0,"volume":15956.0,"ma5":208600.0,"ma20":211650.0,"ma60":220650.0,"bb_upper":220234.56,"bb_lower":203065.44,"vwap":212573.47,"rsi":47.4,"macd_hist":93.5},{"date":"2026-05-11","open":211000.0,"high":211500.0,"low":204500.0,"close":205000.0,"volume":22055.0,"ma5":208000.0,"ma20":210750.0,"ma60":220608.33,"bb_upper":217993.87,"bb_lower":203506.13,"vwap":211787.62,"rsi":44.6,"macd_hist":-99.8},{"date":"2026-05-12","open":207000.0,"high":211000.0,"low":199900.0,"close":202500.0,"volume":34781.0,"ma5":206200.0,"ma20":210050.0,"ma60":220400.0,"bb_upper":217651.25,"bb_lower":202448.75,"vwap":210845.92,"rsi":43.0,"macd_hist":-351.9},{"date":"2026-05-13","open":209500.0,"high":210500.0,"low":193900.0,"close":194400.0,"volume":23879.0,"ma5":204480.0,"ma20":209270.0,"ma60":219848.33,"bb_upper":219603.41,"bb_lower":198936.59,"vwap":210102.33,"rsi":38.0,"macd_hist":-984.2},{"date":"2026-05-14","open":196900.0,"high":210500.0,"low":193600.0,"close":206500.0,"volume":30433.0,"ma5":203480.0,"ma20":208870.0,"ma60":219506.67,"bb_upper":218967.65,"bb_lower":198772.35,"vwap":209354.07,"rsi":47.7,"macd_hist":-530.4},{"date":"2026-05-15","open":212500.0,"high":221000.0,"low":202500.0,"close":205000.0,"volume":87172.0,"ma5":202680.0,"ma20":208670.0,"ma60":218890.0,"bb_upper":218914.2,"bb_lower":198425.8,"vwap":209253.7,"rsi":46.7,"macd_hist":-286.2},{"date":"2026-05-18","open":209000.0,"high":209000.0,"low":195100.0,"close":198300.0,"volume":22614.0,"ma5":201340.0,"ma20":207810.0,"ma60":218311.67,"bb_upper":218517.38,"bb_lower":197102.62,"vwap":208690.65,"rsi":42.5,"macd_hist":-517.5},{"date":"2026-05-19","open":198900.0,"high":199100.0,"low":187600.0,"close":197800.0,"volume":30934.0,"ma5":200400.0,"ma20":207150.0,"ma60":217891.67,"bb_upper":218628.95,"bb_lower":195671.05,"vwap":207661.12,"rsi":42.2,"macd_hist":-637.8},{"date":"2026-05-20","open":204500.0,"high":206000.0,"low":189000.0,"close":195400.0,"volume":23099.0,"ma5":200600.0,"ma20":206370.0,"ma60":217390.0,"bb_upper":218825.92,"bb_lower":193914.08,"vwap":207017.03,"rsi":40.7,"macd_hist":-802.0},{"date":"2026-05-21","open":195600.0,"high":202500.0,"low":193800.0,"close":197200.0,"volume":15038.0,"ma5":198740.0,"ma20":205630.0,"ma60":216835.0,"bb_upper":218431.33,"bb_lower":192828.67,"vwap":206474.58,"rsi":42.4,"macd_hist":-715.3},{"date":"2026-05-22","open":199200.0,"high":205000.0,"low":194500.0,"close":202000.0,"volume":13675.0,"ma5":198140.0,"ma20":205105.0,"ma60":216343.33,"bb_upper":217577.03,"bb_lower":192632.97,"vwap":206130.6,"rsi":46.7,"macd_hist":-282.8},{"date":"2026-05-26","open":205500.0,"high":209000.0,"low":194000.0,"close":194400.0,"volume":14589.0,"ma5":197360.0,"ma20":203975.0,"ma60":215416.67,"bb_upper":215996.36,"bb_lower":191953.64,"vwap":205396.3,"rsi":41.4,"macd_hist":-446.9},{"date":"2026-05-27","open":195000.0,"high":199900.0,"low":194400.0,"close":196400.0,"volume":23345.0,"ma5":197080.0,"ma20":203245.0,"ma60":214606.67,"bb_upper":215243.33,"bb_lower":191246.67,"vwap":204663.35,"rsi":43.2,"macd_hist":-362.6},{"date":"2026-05-28","open":196400.0,"high":199400.0,"low":191100.0,"close":195500.0,"volume":19980.0,"ma5":197100.0,"ma20":202570.0,"ma60":213706.67,"bb_upper":214723.08,"bb_lower":190416.92,"vwap":204025.33,"rsi":42.6,"macd_hist":-311.4},{"date":"2026-05-29","open":196000.0,"high":200500.0,"low":189300.0,"close":191500.0,"volume":28050.0,"ma5":195960.0,"ma20":201845.0,"ma60":212831.67,"bb_upper":214837.54,"bb_lower":188852.46,"vwap":203320.26,"rsi":39.8,"macd_hist":-480.7},{"date":"2026-06-01","open":192100.0,"high":193300.0,"low":184500.0,"close":185100.0,"volume":13498.0,"ma5":192580.0,"ma20":200500.0,"ma60":212350.0,"bb_upper":214589.34,"bb_lower":186410.66,"vwap":202580.64,"rsi":35.7,"macd_hist":-931.4},{"date":"2026-06-02","open":182900.0,"high":188000.0,"low":177600.0,"close":181300.0,"volume":16401.0,"ma5":189960.0,"ma20":199165.0,"ma60":211588.33,"bb_upper":215189.1,"bb_lower":183140.9,"vwap":201742.34,"rsi":33.5,"macd_hist":-1366.8},{"date":"2026-06-04","open":186000.0,"high":187800.0,"low":178800.0,"close":183200.0,"volume":18957.0,"ma5":187320.0,"ma20":197750.0,"ma60":210800.0,"bb_upper":214180.72,"bb_lower":181319.28,"vwap":200693.71,"rsi":35.7,"macd_hist":-1402.9},{"date":"2026-06-05","open":189000.0,"high":189000.0,"low":178400.0,"close":186000.0,"volume":15850.0,"ma5":185420.0,"ma20":196900.0,"ma60":210216.67,"bb_upper":213934.95,"bb_lower":179865.05,"vwap":199934.56,"rsi":38.8,"macd_hist":-1126.2},{"date":"2026-06-08","open":186000.0,"high":186000.0,"low":170300.0,"close":172500.0,"volume":23054.0,"ma5":181620.0,"ma20":194950.0,"ma60":209383.33,"bb_upper":213781.94,"bb_lower":176118.06,"vwap":198499.52,"rsi":31.0,"macd_hist":-1705.6},{"date":"2026-06-09","open":173400.0,"high":187000.0,"low":173400.0,"close":182400.0,"volume":15392.0,"ma5":181080.0,"ma20":193620.0,"ma60":208581.67,"bb_upper":212026.36,"bb_lower":175213.64,"vwap":197524.52,"rsi":40.4,"macd_hist":-1294.1},{"date":"2026-06-10","open":176800.0,"high":188400.0,"low":176800.0,"close":185500.0,"volume":20419.0,"ma5":181920.0,"ma20":192645.0,"ma60":207706.67,"bb_upper":210572.86,"bb_lower":174717.14,"vwap":196518.77,"rsi":43.0,"macd_hist":-713.9},{"date":"2026-06-11","open":185600.0,"high":188500.0,"low":178600.0,"close":185300.0,"volume":30544.0,"ma5":182340.0,"ma20":191785.0,"ma60":207078.33,"bb_upper":209369.24,"bb_lower":174200.76,"vwap":195174.13,"rsi":42.9,"macd_hist":-267.5},{"date":"2026-06-12","open":199000.0,"high":199000.0,"low":184100.0,"close":186500.0,"volume":17845.0,"ma5":182440.0,"ma20":191390.0,"ma60":206536.67,"bb_upper":209081.5,"bb_lower":173698.5,"vwap":194757.41,"rsi":44.0,"macd_hist":161.6},{"date":"2026-06-15","open":189200.0,"high":194600.0,"low":188250.0,"close":190400.0,"volume":8984.0,"ma5":186020.0,"ma20":190585.0,"ma60":205960.0,"bb_upper":206783.8,"bb_lower":174386.2,"vwap":194104.25,"rsi":47.6,"macd_hist":729.3},{"date":"2026-06-16","open":188900.0,"high":193600.0,"low":187000.0,"close":188300.0,"volume":9130.0,"ma5":187200.0,"ma20":189750.0,"ma60":205140.0,"bb_upper":204474.77,"bb_lower":175025.23,"vwap":190478.38,"rsi":45.9,"macd_hist":969.6},{"date":"2026-06-17","open":188100.0,"high":193000.0,"low":184300.0,"close":184800.0,"volume":8972.0,"ma5":187060.0,"ma20":189075.0,"ma60":204528.33,"bb_upper":203381.26,"bb_lower":174768.74,"vwap":189767.77,"rsi":43.1,"macd_hist":900.5},{"date":"2026-06-18","open":181200.0,"high":187000.0,"low":176100.0,"close":176100.0,"volume":12913.0,"ma5":185220.0,"ma20":187990.0,"ma60":203680.0,"bb_upper":202792.97,"bb_lower":173187.03,"vwap":188949.23,"rsi":37.2,"macd_hist":307.3},{"date":"2026-06-19","open":179800.0,"high":181000.0,"low":173500.0,"close":181000.0,"volume":13135.0,"ma5":184120.0,"ma20":187270.0,"ma60":203096.67,"bb_upper":201955.78,"bb_lower":172584.22,"vwap":188011.56,"rsi":42.0,"macd_hist":283.7},{"date":"2026-06-22","open":181000.0,"high":181000.0,"low":166700.0,"close":166700.0,"volume":20287.0,"ma5":179380.0,"ma20":185745.0,"ma60":202166.67,"bb_upper":202303.98,"bb_lower":169186.02,"vwap":186610.63,"rsi":33.8,"macd_hist":-607.4},{"date":"2026-06-23","open":166700.0,"high":173800.0,"low":164600.0,"close":167800.0,"volume":14652.0,"ma5":175280.0,"ma20":184035.0,"ma60":201288.33,"bb_upper":200589.63,"bb_lower":167480.37,"vwap":185304.62,"rsi":34.9,"macd_hist":-1011.4},{"date":"2026-06-24","open":172000.0,"high":172000.0,"low":156800.0,"close":161000.0,"volume":23294.0,"ma5":170520.0,"ma20":182365.0,"ma60":200321.67,"bb_upper":201110.75,"bb_lower":163619.25,"vwap":183288.57,"rsi":31.5,"macd_hist":-1590.8},{"date":"2026-06-25","open":164000.0,"high":173900.0,"low":160000.0,"close":170000.0,"volume":18997.0,"ma5":169300.0,"ma20":181045.0,"ma60":199446.67,"bb_upper":199342.14,"bb_lower":162747.86,"vwap":181550.81,"rsi":39.8,"macd_hist":-1237.8},{"date":"2026-06-26","open":166400.0,"high":168500.0,"low":162100.0,"close":164600.0,"volume":16503.0,"ma5":166020.0,"ma20":179500.0,"ma60":198473.33,"bb_upper":197876.07,"bb_lower":161123.93,"vwap":179972.7,"rsi":36.9,"macd_hist":-1235.1},{"date":"2026-06-29","open":165700.0,"high":177700.0,"low":162000.0,"close":176500.0,"volume":18303.0,"ma5":167980.0,"ma20":178750.0,"ma60":197765.0,"bb_upper":196268.29,"bb_lower":161231.71,"vwap":178395.78,"rsi":46.1,"macd_hist":-345.1},{"date":"2026-06-30","open":176000.0,"high":177800.0,"low":162500.0,"close":163100.0,"volume":19421.0,"ma5":167040.0,"ma20":177650.0,"ma60":196733.33,"bb_upper":196220.66,"bb_lower":159079.34,"vwap":177432.46,"rsi":39.2,"macd_hist":-559.6},{"date":"2026-07-01","open":166300.0,"high":169800.0,"low":162200.0,"close":168200.0,"volume":15790.0,"ma5":168480.0,"ma20":176995.0,"ma60":195936.67,"bb_upper":195943.85,"bb_lower":158046.15,"vwap":176706.0,"rsi":42.7,"macd_hist":-273.1},{"date":"2026-07-02","open":180500.0,"high":190900.0,"low":167200.0,"close":180000.0,"volume":23253.0,"ma5":170480.0,"ma20":176835.0,"ma60":195428.33,"bb_upper":195616.54,"bb_lower":158053.46,"vwap":176525.74,"rsi":50.0,"macd_hist":740.6},{"date":"2026-07-03","open":188900.0,"high":189000.0,"low":175200.0,"close":181800.0,"volume":11213.0,"ma5":173920.0,"ma20":176625.0,"ma60":195066.67,"bb_upper":195065.9,"bb_lower":158184.1,"vwap":176337.26,"rsi":51.0,"macd_hist":1517.0},{"date":"2026-07-06","open":180700.0,"high":186200.0,"low":178500.0,"close":181900.0,"volume":7424.0,"ma5":175000.0,"ma20":177095.0,"ma60":194673.33,"bb_upper":195572.35,"bb_lower":158617.65,"vwap":176475.56,"rsi":51.0,"macd_hist":1992.1},{"date":"2026-07-07","open":181900.0,"high":190000.0,"low":177600.0,"close":190000.0,"volume":11897.0,"ma5":180380.0,"ma20":177475.0,"ma60":194248.33,"bb_upper":196708.84,"bb_lower":158241.16,"vwap":176609.05,"rsi":55.7,"macd_hist":2759.4},{"date":"2026-07-08","open":193700.0,"high":194000.0,"low":180300.0,"close":185200.0,"volume":21181.0,"ma5":183780.0,"ma20":177460.0,"ma60":193618.33,"bb_upper":196667.94,"bb_lower":158252.06,"vwap":176817.34,"rsi":52.5,"macd_hist":2840.1},{"date":"2026-07-09","open":192100.0,"high":192100.0,"low":183000.0,"close":188000.0,"volume":20542.0,"ma5":185380.0,"ma20":177595.0,"ma60":193143.33,"bb_upper":197071.03,"bb_lower":158118.97,"vwap":176817.63,"rsi":54.2,"macd_hist":2964.8},{"date":"2026-07-10","open":189800.0,"high":199500.0,"low":185500.0,"close":189300.0,"volume":12512.0,"ma5":186880.0,"ma20":177735.0,"ma60":192798.33,"bb_upper":197518.38,"bb_lower":157951.62,"vwap":176655.55,"rsi":55.0,"macd_hist":3008.0},{"date":"2026-07-13","open":189400.0,"high":199000.0,"low":189400.0,"close":193100.0,"volume":13338.0,"ma5":189120.0,"ma20":177870.0,"ma60":192441.67,"bb_upper":198050.15,"bb_lower":157689.85,"vwap":176973.68,"rsi":57.3,"macd_hist":3150.5},{"date":"2026-07-14","open":195000.0,"high":199800.0,"low":185800.0,"close":185800.0,"volume":25052.0,"ma5":188280.0,"ma20":177745.0,"ma60":192055.0,"bb_upper":197682.64,"bb_lower":157807.36,"vwap":177650.46,"rsi":51.8,"macd_hist":2632.3},{"date":"2026-07-15","open":187800.0,"high":193500.0,"low":186000.0,"close":188200.0,"volume":13532.0,"ma5":188880.0,"ma20":177915.0,"ma60":191600.0,"bb_upper":198161.51,"bb_lower":157668.49,"vwap":177859.21,"rsi":53.4,"macd_hist":2340.2},{"date":"2026-07-16","open":188200.0,"high":193400.0,"low":185500.0,"close":191200.0,"volume":12482.0,"ma5":189520.0,"ma20":178670.0,"ma60":191270.0,"bb_upper":199740.92,"bb_lower":157599.08,"vwap":178243.09,"rsi":55.3,"macd_hist":2238.0},{"date":"2026-07-20","open":193300.0,"high":197600.0,"low":186000.0,"close":187400.0,"volume":9844.0,"ma5":189140.0,"ma20":178990.0,"ma60":190876.67,"bb_upper":200401.55,"bb_lower":157578.45,"vwap":178594.03,"rsi":52.3,"macd_hist":1821.2},{"date":"2026-07-21","open":185400.0,"high":193900.0,"low":184800.0,"close":190900.0,"volume":6588.0,"ma5":188700.0,"ma20":180200.0,"ma60":190525.0,"bb_upper":201421.54,"bb_lower":158978.46,"vwap":179287.02,"rsi":54.8,"macd_hist":1690.7},{"date":"2026-07-22","open":191000.0,"high":194800.0,"low":189500.0,"close":191000.0,"volume":9123.0,"ma5":189740.0,"ma20":181360.0,"ma60":190166.67,"bb_upper":202261.51,"bb_lower":160458.49,"vwap":180152.29,"rsi":54.8,"macd_hist":1525.7}]