[{"date":"2026-01-22","open":175300.0,"high":182700.0,"low":174700.0,"close":178800.0,"volume":465291.0,"ma5":null,"ma20":null,"ma60":null,"bb_upper":null,"bb_lower":null,"vwap":null,"rsi":50.0,"macd_hist":0.0},{"date":"2026-01-23","open":180500.0,"high":185900.0,"low":177000.0,"close":185100.0,"volume":518798.0,"ma5":null,"ma20":null,"ma60":null,"bb_upper":null,"bb_lower":null,"vwap":null,"rsi":50.0,"macd_hist":402.1},{"date":"2026-01-26","open":186500.0,"high":189000.0,"low":181700.0,"close":182200.0,"volume":304082.0,"ma5":null,"ma20":null,"ma60":null,"bb_upper":null,"bb_lower":null,"vwap":null,"rsi":96.6,"macd_hist":447.0},{"date":"2026-01-27","open":184300.0,"high":188600.0,"low":182000.0,"close":187100.0,"volume":250715.0,"ma5":null,"ma20":null,"ma60":null,"bb_upper":null,"bb_lower":null,"vwap":null,"rsi":96.8,"macd_hist":762.5},{"date":"2026-01-28","open":191100.0,"high":197000.0,"low":189000.0,"close":192200.0,"volume":407899.0,"ma5":185080.0,"ma20":null,"ma60":null,"bb_upper":null,"bb_lower":null,"vwap":null,"rsi":97.0,"macd_hist":1242.1},{"date":"2026-01-29","open":200000.0,"high":200000.0,"low":189400.0,"close":192000.0,"volume":426793.0,"ma5":187720.0,"ma20":null,"ma60":null,"bb_upper":null,"bb_lower":null,"vwap":null,"rsi":96.7,"macd_hist":1458.3},{"date":"2026-01-30","open":190100.0,"high":193900.0,"low":187300.0,"close":188300.0,"volume":437998.0,"ma5":188360.0,"ma20":null,"ma60":null,"bb_upper":null,"bb_lower":null,"vwap":null,"rsi":92.0,"macd_hist":1271.4},{"date":"2026-02-02","open":188000.0,"high":188000.0,"low":177900.0,"close":179000.0,"volume":267951.0,"ma5":187720.0,"ma20":null,"ma60":null,"bb_upper":null,"bb_lower":null,"vwap":null,"rsi":81.2,"macd_hist":481.4},{"date":"2026-02-03","open":183100.0,"high":186500.0,"low":179100.0,"close":186300.0,"volume":273276.0,"ma5":187560.0,"ma20":null,"ma60":null,"bb_upper":null,"bb_lower":null,"vwap":null,"rsi":82.9,"macd_hist":413.0},{"date":"2026-02-04","open":185700.0,"high":199600.0,"low":185100.0,"close":197500.0,"volume":520691.0,"ma5":188620.0,"ma20":null,"ma60":null,"bb_upper":null,"bb_lower":null,"vwap":null,"rsi":85.1,"macd_hist":1048.5},{"date":"2026-02-05","open":195400.0,"high":203000.0,"low":191000.0,"close":191700.0,"volume":347872.0,"ma5":188560.0,"ma20":null,"ma60":null,"bb_upper":null,"bb_lower":null,"vwap":null,"rsi":79.3,"macd_hist":1004.6},{"date":"2026-02-06","open":185100.0,"high":187000.0,"low":180800.0,"close":184300.0,"volume":344188.0,"ma5":187760.0,"ma20":null,"ma60":null,"bb_upper":null,"bb_lower":null,"vwap":null,"rsi":72.6,"macd_hist":432.7},{"date":"2026-02-09","open":192000.0,"high":196100.0,"low":190500.0,"close":193000.0,"volume":324928.0,"ma5":190560.0,"ma20":null,"ma60":null,"bb_upper":null,"bb_lower":null,"vwap":null,"rsi":75.3,"macd_hist":586.3},{"date":"2026-02-10","open":200000.0,"high":200500.0,"low":194900.0,"close":197700.0,"volume":347107.0,"ma5":192840.0,"ma20":null,"ma60":null,"bb_upper":null,"bb_lower":null,"vwap":null,"rsi":76.6,"macd_hist":930.1},{"date":"2026-02-11","open":200500.0,"high":201500.0,"low":197600.0,"close":200000.0,"volume":248463.0,"ma5":193340.0,"ma20":null,"ma60":null,"bb_upper":null,"bb_lower":null,"vwap":null,"rsi":77.2,"macd_hist":1219.7},{"date":"2026-02-12","open":205500.0,"high":207000.0,"low":201000.0,"close":205000.0,"volume":319058.0,"ma5":196000.0,"ma20":null,"ma60":null,"bb_upper":null,"bb_lower":null,"vwap":null,"rsi":78.6,"macd_hist":1629.7},{"date":"2026-02-13","open":203500.0,"high":214500.0,"low":203500.0,"close":205500.0,"volume":275781.0,"ma5":200240.0,"ma20":null,"ma60":null,"bb_upper":null,"bb_lower":null,"vwap":null,"rsi":78.7,"macd_hist":1802.7},{"date":"2026-02-19","open":218000.0,"high":221000.0,"low":206000.0,"close":209000.0,"volume":394865.0,"ma5":203440.0,"ma20":null,"ma60":null,"bb_upper":null,"bb_lower":null,"vwap":null,"rsi":79.7,"macd_hist":2005.6},{"date":"2026-02-20","open":207500.0,"high":226500.0,"low":207500.0,"close":219000.0,"volume":527945.0,"ma5":207700.0,"ma20":null,"ma60":null,"bb_upper":null,"bb_lower":null,"vwap":null,"rsi":82.3,"macd_hist":2626.7},{"date":"2026-02-23","open":246000.0,"high":252000.0,"low":227000.0,"close":232000.0,"volume":1080275.0,"ma5":214100.0,"ma20":195285.0,"ma60":null,"bb_upper":222420.78,"bb_lower":168149.22,"vwap":199714.25,"rsi":84.9,"macd_hist":3662.9},{"date":"2026-02-24","open":235500.0,"high":235500.0,"low":220000.0,"close":224000.0,"volume":498247.0,"ma5":217900.0,"ma20":197545.0,"ma60":null,"bb_upper":226375.94,"bb_lower":168714.06,"vwap":202561.16,"rsi":77.3,"macd_hist":3556.4},{"date":"2026-02-25","open":229500.0,"high":259500.0,"low":224500.0,"close":246000.0,"volume":838515.0,"ma5":226000.0,"ma20":200590.0,"ma60":null,"bb_upper":236000.01,"bb_lower":165179.99,"vwap":207836.86,"rsi":82.1,"macd_hist":4645.7},{"date":"2026-02-26","open":239000.0,"high":243500.0,"low":232000.0,"close":239000.0,"volume":906126.0,"ma5":232000.0,"ma20":203430.0,"ma60":null,"bb_upper":241630.86,"bb_lower":165229.14,"vwap":211669.25,"rsi":76.5,"macd_hist":4566.1},{"date":"2026-02-27","open":240000.0,"high":241000.0,"low":227000.0,"close":230000.0,"volume":672911.0,"ma5":234200.0,"ma20":205575.0,"ma60":null,"bb_upper":244721.09,"bb_lower":166428.91,"vwap":213845.59,"rsi":70.0,"macd_hist":3620.0},{"date":"2026-03-03","open":221000.0,"high":236250.0,"low":220000.0,"close":221500.0,"volume":633693.0,"ma5":232100.0,"ma20":207040.0,"ma60":null,"bb_upper":246271.48,"bb_lower":167808.52,"vwap":215524.29,"rsi":64.5,"macd_hist":2204.1},{"date":"2026-03-04","open":215000.0,"high":215500.0,"low":196100.0,"close":197500.0,"volume":624203.0,"ma5":226800.0,"ma20":207315.0,"ma60":null,"bb_upper":246177.96,"bb_lower":168452.04,"vwap":215673.51,"rsi":51.9,"macd_hist":-426.4},{"date":"2026-03-05","open":212000.0,"high":219500.0,"low":205500.0,"close":214000.0,"volume":542592.0,"ma5":220400.0,"ma20":208600.0,"ma60":null,"bb_upper":246503.37,"bb_lower":170696.63,"vwap":216661.36,"rsi":58.0,"macd_hist":-1094.5},{"date":"2026-03-06","open":203500.0,"high":211750.0,"low":201000.0,"close":210000.0,"volume":353025.0,"ma5":214600.0,"ma20":210150.0,"ma60":null,"bb_upper":245399.22,"bb_lower":174900.78,"vwap":217274.93,"rsi":56.1,"macd_hist":-1803.5},{"date":"2026-03-09","open":192000.0,"high":200500.0,"low":190500.0,"close":200500.0,"volume":339266.0,"ma5":208700.0,"ma20":210860.0,"ma60":null,"bb_upper":244627.4,"bb_lower":177092.6,"vwap":217499.82,"rsi":51.9,"macd_hist":-2847.8},{"date":"2026-03-10","open":213000.0,"high":215000.0,"low":206000.0,"close":211500.0,"volume":255956.0,"ma5":206700.0,"ma20":211560.0,"ma60":null,"bb_upper":244736.55,"bb_lower":178383.45,"vwap":218562.62,"rsi":56.0,"macd_hist":-2732.8},{"date":"2026-03-11","open":223000.0,"high":232000.0,"low":220500.0,"close":226500.0,"volume":520055.0,"ma5":212500.0,"ma20":213300.0,"ma60":null,"bb_upper":245732.86,"bb_lower":180867.14,"vwap":219772.59,"rsi":60.9,"macd_hist":-1635.6},{"date":"2026-03-12","open":226500.0,"high":226500.0,"low":216500.0,"close":218500.0,"volume":526197.0,"ma5":213400.0,"ma20":215010.0,"ma60":null,"bb_upper":244475.55,"bb_lower":185544.45,"vwap":221012.54,"rsi":57.3,"macd_hist":-1444.5},{"date":"2026-03-13","open":209000.0,"high":219000.0,"low":208500.0,"close":216000.0,"volume":436847.0,"ma5":214600.0,"ma20":216160.0,"ma60":null,"bb_upper":243743.85,"bb_lower":188576.15,"vwap":221611.33,"rsi":56.1,"macd_hist":-1477.0},{"date":"2026-03-16","open":213500.0,"high":217500.0,"low":209500.0,"close":212000.0,"volume":236922.0,"ma5":216900.0,"ma20":216875.0,"ma60":null,"bb_upper":243154.62,"bb_lower":190595.38,"vwap":222223.15,"rsi":54.3,"macd_hist":-1740.3},{"date":"2026-03-17","open":217500.0,"high":221000.0,"low":214000.0,"close":217000.0,"volume":208804.0,"ma5":218000.0,"ma20":217725.0,"ma60":null,"bb_upper":242777.52,"bb_lower":192672.48,"vwap":222672.08,"rsi":56.2,"macd_hist":-1556.1},{"date":"2026-03-18","open":228500.0,"high":245500.0,"low":225000.0,"close":235000.0,"volume":598488.0,"ma5":219700.0,"ma20":219225.0,"ma60":null,"bb_upper":244659.07,"bb_lower":193790.93,"vwap":223945.06,"rsi":62.4,"macd_hist":-268.0},{"date":"2026-03-19","open":229500.0,"high":237000.0,"low":227500.0,"close":230500.0,"volume":234935.0,"ma5":222100.0,"ma20":220475.0,"ma60":null,"bb_upper":245523.32,"bb_lower":195426.68,"vwap":224545.01,"rsi":60.1,"macd_hist":209.3},{"date":"2026-03-20","open":232000.0,"high":232000.0,"low":220000.0,"close":231500.0,"volume":569040.0,"ma5":225200.0,"ma20":221600.0,"ma60":null,"bb_upper":246498.95,"bb_lower":196701.05,"vwap":225188.61,"rsi":60.5,"macd_hist":503.9},{"date":"2026-03-23","open":225500.0,"high":225500.0,"low":214000.0,"close":217500.0,"volume":481137.0,"ma5":226300.0,"ma20":221525.0,"ma60":null,"bb_upper":246465.93,"bb_lower":196584.07,"vwap":225282.73,"rsi":53.4,"macd_hist":-289.9},{"date":"2026-03-24","open":228000.0,"high":228000.0,"low":213000.0,"close":222000.0,"volume":312515.0,"ma5":227300.0,"ma20":221025.0,"ma60":null,"bb_upper":245477.91,"bb_lower":196572.09,"vwap":223853.0,"rsi":55.2,"macd_hist":-543.0},{"date":"2026-03-25","open":233000.0,"high":235500.0,"low":226000.0,"close":227500.0,"volume":493421.0,"ma5":225800.0,"ma20":221200.0,"ma60":null,"bb_upper":245792.25,"bb_lower":196607.75,"vwap":224011.38,"rsi":57.4,"macd_hist":-378.9},{"date":"2026-03-26","open":229000.0,"high":229000.0,"low":220500.0,"close":222000.0,"volume":384833.0,"ma5":224100.0,"ma20":220000.0,"ma60":null,"bb_upper":241664.91,"bb_lower":198335.09,"vwap":222267.69,"rsi":54.6,"macd_hist":-663.0},{"date":"2026-03-27","open":218000.0,"high":224500.0,"low":215000.0,"close":223000.0,"volume":310598.0,"ma5":222400.0,"ma20":219200.0,"ma60":null,"bb_upper":239013.34,"bb_lower":199386.66,"vwap":220567.5,"rsi":55.0,"macd_hist":-796.8},{"date":"2026-03-30","open":209500.0,"high":221000.0,"low":209000.0,"close":219500.0,"volume":286890.0,"ma5":222800.0,"ma20":218675.0,"ma60":null,"bb_upper":237828.88,"bb_lower":199521.12,"vwap":219452.62,"rsi":53.1,"macd_hist":-1114.8},{"date":"2026-03-31","open":213000.0,"high":217500.0,"low":208000.0,"close":210500.0,"volume":347780.0,"ma5":220500.0,"ma20":218125.0,"ma60":null,"bb_upper":237566.88,"bb_lower":198683.12,"vwap":218623.19,"rsi":48.4,"macd_hist":-1879.9},{"date":"2026-04-01","open":228000.0,"high":229500.0,"low":220000.0,"close":225000.0,"volume":381511.0,"ma5":220000.0,"ma20":219500.0,"ma60":null,"bb_upper":236541.74,"bb_lower":202458.26,"vwap":220170.4,"rsi":55.2,"macd_hist":-1381.3},{"date":"2026-04-02","open":228500.0,"high":231500.0,"low":214000.0,"close":217000.0,"volume":351480.0,"ma5":219000.0,"ma20":219650.0,"ma60":null,"bb_upper":236540.05,"bb_lower":202759.95,"vwap":220710.87,"rsi":51.2,"macd_hist":-1549.4},{"date":"2026-04-03","open":223000.0,"high":227000.0,"low":220000.0,"close":221000.0,"volume":141907.0,"ma5":218600.0,"ma20":220200.0,"ma60":null,"bb_upper":236472.03,"bb_lower":203927.97,"vwap":221372.98,"rsi":53.1,"macd_hist":-1357.3},{"date":"2026-04-06","open":222000.0,"high":229500.0,"low":222000.0,"close":226000.0,"volume":163542.0,"ma5":219900.0,"ma20":221475.0,"ma60":null,"bb_upper":235014.32,"bb_lower":207935.68,"vwap":222607.55,"rsi":55.3,"macd_hist":-882.5},{"date":"2026-04-07","open":230500.0,"high":234500.0,"low":220500.0,"close":222000.0,"volume":209007.0,"ma5":222200.0,"ma20":222000.0,"ma60":null,"bb_upper":234698.94,"bb_lower":209301.06,"vwap":223115.21,"rsi":53.1,"macd_hist":-827.9},{"date":"2026-04-08","open":240500.0,"high":243000.0,"low":230500.0,"close":238500.0,"volume":402137.0,"ma5":224900.0,"ma20":222600.0,"ma60":null,"bb_upper":237187.67,"bb_lower":208012.33,"vwap":223686.56,"rsi":60.2,"macd_hist":270.8},{"date":"2026-04-09","open":234500.0,"high":236500.0,"low":224000.0,"close":230000.0,"volume":453988.0,"ma5":227500.0,"ma20":223175.0,"ma60":null,"bb_upper":237987.07,"bb_lower":208362.93,"vwap":224345.82,"rsi":55.5,"macd_hist":370.1},{"date":"2026-04-10","open":233000.0,"high":237000.0,"low":232000.0,"close":234500.0,"volume":324396.0,"ma5":230200.0,"ma20":224100.0,"ma60":null,"bb_upper":239330.16,"bb_lower":208869.84,"vwap":225447.63,"rsi":57.4,"macd_hist":666.7},{"date":"2026-04-13","open":233500.0,"high":236000.0,"low":231000.0,"close":235000.0,"volume":381274.0,"ma5":232000.0,"ma20":225250.0,"ma60":null,"bb_upper":240101.9,"bb_lower":210398.1,"vwap":226330.01,"rsi":57.6,"macd_hist":814.6},{"date":"2026-04-14","open":238500.0,"high":250000.0,"low":238500.0,"close":246000.0,"volume":431551.0,"ma5":236800.0,"ma20":226700.0,"ma60":null,"bb_upper":243671.8,"bb_lower":209728.2,"vwap":227688.56,"rsi":62.2,"macd_hist":1529.7},{"date":"2026-04-15","open":252000.0,"high":262500.0,"low":251500.0,"close":258000.0,"volume":423868.0,"ma5":240700.0,"ma20":227850.0,"ma60":null,"bb_upper":249626.62,"bb_lower":206073.38,"vwap":228830.27,"rsi":66.4,"macd_hist":2623.2},{"date":"2026-04-16","open":258000.0,"high":262000.0,"low":255000.0,"close":258000.0,"volume":280130.0,"ma5":246300.0,"ma20":229225.0,"ma60":null,"bb_upper":254840.53,"bb_lower":203609.47,"vwap":229895.8,"rsi":66.4,"macd_hist":3124.8},{"date":"2026-04-17","open":256000.0,"high":257000.0,"low":252000.0,"close":253500.0,"volume":170779.0,"ma5":250100.0,"ma20":230325.0,"ma60":null,"bb_upper":258146.38,"bb_lower":202503.62,"vwap":230685.76,"rsi":63.3,"macd_hist":2934.8},{"date":"2026-04-20","open":256500.0,"high":257500.0,"low":251000.0,"close":253500.0,"volume":173309.0,"ma5":253800.0,"ma20":232125.0,"ma60":null,"bb_upper":261087.54,"bb_lower":203162.46,"vwap":232189.75,"rsi":63.3,"macd_hist":2601.7},{"date":"2026-04-21","open":254000.0,"high":259000.0,"low":252750.0,"close":256000.0,"volume":208078.0,"ma5":255800.0,"ma20":233825.0,"ma60":216711.67,"bb_upper":264240.15,"bb_lower":203409.85,"vwap":233524.14,"rsi":64.4,"macd_hist":2350.1},{"date":"2026-04-22","open":253500.0,"high":255500.0,"low":246000.0,"close":247500.0,"volume":282061.0,"ma5":253700.0,"ma20":234825.0,"ma60":217856.67,"bb_upper":265676.55,"bb_lower":203973.45,"vwap":234581.01,"rsi":58.2,"macd_hist":1455.3},{"date":"2026-04-23","open":255500.0,"high":260000.0,"low":251000.0,"close":255500.0,"volume":476920.0,"ma5":253200.0,"ma20":236500.0,"ma60":219030.0,"bb_upper":268049.46,"bb_lower":204950.54,"vwap":236856.82,"rsi":61.9,"macd_hist":1254.0},{"date":"2026-04-24","open":253500.0,"high":255500.0,"low":244000.0,"close":244500.0,"volume":275279.0,"ma5":251400.0,"ma20":237575.0,"ma60":220068.33,"bb_upper":268649.23,"bb_lower":206500.77,"vwap":238161.47,"rsi":54.7,"macd_hist":282.5},{"date":"2026-04-27","open":244500.0,"high":250500.0,"low":241500.0,"close":250000.0,"volume":328458.0,"ma5":250700.0,"ma20":239100.0,"ma60":221116.67,"bb_upper":269423.87,"bb_lower":208776.13,"vwap":239647.91,"rsi":57.4,"macd_hist":-68.4},{"date":"2026-04-28","open":248000.0,"high":255000.0,"low":246500.0,"close":252000.0,"volume":293762.0,"ma5":249900.0,"ma20":241175.0,"ma60":222113.33,"bb_upper":268819.88,"bb_lower":213530.12,"vwap":241760.42,"rsi":58.4,"macd_hist":-235.2},{"date":"2026-04-29","open":252000.0,"high":255000.0,"low":248500.0,"close":252000.0,"volume":191784.0,"ma5":250800.0,"ma20":242525.0,"ma60":223113.33,"bb_upper":269472.27,"bb_lower":215577.73,"vwap":243167.21,"rsi":58.4,"macd_hist":-405.0},{"date":"2026-04-30","open":249500.0,"high":252500.0,"low":246500.0,"close":249500.0,"volume":1573209.0,"ma5":249600.0,"ma20":244150.0,"ma60":224133.33,"bb_upper":268401.1,"bb_lower":219898.9,"vwap":245646.21,"rsi":56.5,"macd_hist":-726.3},{"date":"2026-05-04","open":256000.0,"high":270000.0,"low":251500.0,"close":265000.0,"volume":694674.0,"ma5":253700.0,"ma20":246350.0,"ma60":225566.67,"bb_upper":269725.88,"bb_lower":222974.12,"vwap":247550.69,"rsi":64.1,"macd_hist":24.6},{"date":"2026-05-06","open":280500.0,"high":308000.0,"low":270000.0,"close":298000.0,"volume":787419.0,"ma5":263300.0,"ma20":249950.0,"ma60":227428.33,"bb_upper":281035.45,"bb_lower":218864.55,"vwap":252161.02,"rsi":74.3,"macd_hist":2524.9},{"date":"2026-05-07","open":304000.0,"high":307000.0,"low":294500.0,"close":300000.0,"volume":549698.0,"ma5":272900.0,"ma20":253850.0,"ma60":229136.67,"bb_upper":289419.21,"bb_lower":218280.79,"vwap":255850.57,"rsi":74.8,"macd_hist":4006.6},{"date":"2026-05-08","open":302000.0,"high":303000.0,"low":286000.0,"close":295000.0,"volume":389032.0,"ma5":281500.0,"ma20":256675.0,"ma60":230858.33,"bb_upper":295898.08,"bb_lower":217451.92,"vwap":258445.28,"rsi":71.3,"macd_hist":4316.3},{"date":"2026-05-11","open":310000.0,"high":314500.0,"low":298000.0,"close":299500.0,"volume":469336.0,"ma5":291500.0,"ma20":260150.0,"ma60":232778.33,"bb_upper":301669.94,"bb_lower":218630.06,"vwap":262376.19,"rsi":72.5,"macd_hist":4471.6},{"date":"2026-05-12","open":306500.0,"high":316500.0,"low":291500.0,"close":299500.0,"volume":537010.0,"ma5":298400.0,"ma20":263400.0,"ma60":234553.33,"bb_upper":306607.7,"bb_lower":220192.3,"vwap":265806.45,"rsi":72.5,"macd_hist":4224.6},{"date":"2026-05-13","open":297000.0,"high":308000.0,"low":289500.0,"close":306000.0,"volume":331525.0,"ma5":300000.0,"ma20":266950.0,"ma60":236358.33,"bb_upper":311962.16,"bb_lower":221937.84,"vwap":268495.91,"rsi":74.4,"macd_hist":4143.5},{"date":"2026-05-14","open":310000.0,"high":334500.0,"low":308000.0,"close":330000.0,"volume":622246.0,"ma5":306000.0,"ma20":271150.0,"ma60":238525.0,"bb_upper":323076.16,"bb_lower":219223.84,"vwap":273447.3,"rsi":79.8,"macd_hist":5278.2},{"date":"2026-05-15","open":332000.0,"high":339500.0,"low":300000.0,"close":310000.0,"volume":665867.0,"ma5":309000.0,"ma20":273750.0,"ma60":240275.0,"bb_upper":328056.63,"bb_lower":219443.37,"vwap":277264.0,"rsi":67.0,"macd_hist":4295.3},{"date":"2026-05-18","open":307500.0,"high":324000.0,"low":302000.0,"close":313500.0,"volume":394802.0,"ma5":311800.0,"ma20":276525.0,"ma60":242075.0,"bb_upper":333068.86,"bb_lower":219981.14,"vwap":279332.72,"rsi":68.0,"macd_hist":3526.6},{"date":"2026-05-19","open":314000.0,"high":325500.0,"low":307500.0,"close":312000.0,"volume":562673.0,"ma5":314300.0,"ma20":279450.0,"ma60":243791.67,"bb_upper":337021.83,"bb_lower":221878.17,"vwap":281817.32,"rsi":67.1,"macd_hist":2605.4},{"date":"2026-05-20","open":316500.0,"high":323000.0,"low":293500.0,"close":312000.0,"volume":479750.0,"ma5":315500.0,"ma20":282375.0,"ma60":245341.67,"bb_upper":340338.58,"bb_lower":224411.42,"vwap":283607.17,"rsi":67.1,"macd_hist":1726.6},{"date":"2026-05-21","open":339500.0,"high":359000.0,"low":331500.0,"close":355000.0,"volume":436740.0,"ma5":320500.0,"ma20":287325.0,"ma60":247391.67,"bb_upper":352290.8,"bb_lower":222359.2,"vwap":286904.62,"rsi":77.2,"macd_hist":3660.7},{"date":"2026-05-22","open":355000.0,"high":370000.0,"low":352500.0,"close":364500.0,"volume":424209.0,"ma5":331400.0,"ma20":293175.0,"ma60":249733.33,"bb_upper":363860.57,"bb_lower":222489.43,"vwap":290958.35,"rsi":78.8,"macd_hist":5110.2},{"date":"2026-05-26","open":367000.0,"high":373500.0,"low":344500.0,"close":348000.0,"volume":464462.0,"ma5":338300.0,"ma20":297800.0,"ma60":251433.33,"bb_upper":370190.32,"bb_lower":225409.68,"vwap":295428.45,"rsi":69.9,"macd_hist":4509.2},{"date":"2026-05-27","open":365000.0,"high":370500.0,"low":350500.0,"close":354500.0,"volume":424017.0,"ma5":346800.0,"ma20":303300.0,"ma60":253358.33,"bb_upper":375353.63,"bb_lower":231246.37,"vwap":299175.81,"rsi":71.2,"macd_hist":4111.9},{"date":"2026-05-28","open":351500.0,"high":361000.0,"low":340000.0,"close":357500.0,"volume":474676.0,"ma5":355900.0,"ma20":308675.0,"ma60":255483.33,"bb_upper":380022.39,"bb_lower":237327.61,"vwap":303122.91,"rsi":71.9,"macd_hist":3630.5},{"date":"2026-05-29","open":366500.0,"high":391500.0,"low":355000.0,"close":388500.0,"volume":789483.0,"ma5":362600.0,"ma20":315500.0,"ma60":258266.67,"bb_upper":390062.58,"bb_lower":240937.42,"vwap":309750.16,"rsi":77.5,"macd_hist":4900.1},{"date":"2026-06-01","open":387000.0,"high":420500.0,"low":383000.0,"close":410000.0,"volume":669413.0,"ma5":371700.0,"ma20":323400.0,"ma60":261808.33,"bb_upper":402948.46,"bb_lower":243851.54,"vwap":316098.77,"rsi":80.4,"macd_hist":6583.2},{"date":"2026-06-02","open":421000.0,"high":485000.0,"low":412000.0,"close":480000.0,"volume":772311.0,"ma5":398100.0,"ma20":334925.0,"ma60":266241.67,"bb_upper":433828.08,"bb_lower":236021.92,"vwap":335765.22,"rsi":86.5,"macd_hist":11517.5},{"date":"2026-06-04","open":440000.0,"high":457000.0,"low":417000.0,"close":438000.0,"volume":1025694.0,"ma5":414800.0,"ma20":343575.0,"ma60":270041.67,"bb_upper":446890.7,"bb_lower":240259.3,"vwap":349545.15,"rsi":72.0,"macd_hist":11057.1},{"date":"2026-06-05","open":397000.0,"high":420000.0,"low":395500.0,"close":412500.0,"volume":509906.0,"ma5":425800.0,"ma20":349300.0,"ma60":273575.0,"bb_upper":454651.74,"bb_lower":243948.26,"vwap":356440.4,"rsi":64.9,"macd_hist":8267.2},{"date":"2026-06-08","open":350000.0,"high":392500.0,"low":349500.0,"close":375500.0,"volume":551825.0,"ma5":423200.0,"ma20":353075.0,"ma60":276308.33,"bb_upper":456379.49,"bb_lower":249770.51,"vwap":360043.17,"rsi":56.2,"macd_hist":3410.9},{"date":"2026-06-09","open":383000.0,"high":394500.0,"low":375000.0,"close":393000.0,"volume":492974.0,"ma5":419800.0,"ma20":357975.0,"ma60":279083.33,"bb_upper":458951.53,"bb_lower":256998.47,"vwap":363554.24,"rsi":59.0,"macd_hist":984.1},{"date":"2026-06-10","open":370000.0,"high":379500.0,"low":356000.0,"close":368000.0,"volume":31.0,"ma5":397400.0,"ma20":361400.0,"ma60":281575.0,"bb_upper":458601.69,"bb_lower":264198.31,"vwap":366183.79,"rsi":53.7,"macd_hist":-2507.1},{"date":"2026-06-11","open":354500.0,"high":369500.0,"low":342000.0,"close":365000.0,"volume":762495.0,"ma5":382800.0,"ma20":364675.0,"ma60":284058.33,"bb_upper":457406.23,"bb_lower":271943.77,"vwap":368817.96,"rsi":53.1,"macd_hist":-5072.7},{"date":"2026-06-12","open":392500.0,"high":406500.0,"low":381500.0,"close":385500.0,"volume":398960.0,"ma5":377400.0,"ma20":368650.0,"ma60":286950.0,"bb_upper":457526.67,"bb_lower":279773.33,"vwap":371687.65,"rsi":56.8,"macd_hist":-5412.5},{"date":"2026-06-15","open":404500.0,"high":424000.0,"low":402500.0,"close":423000.0,"volume":445849.0,"ma5":386900.0,"ma20":373300.0,"ma60":290383.33,"bb_upper":463385.57,"bb_lower":283214.43,"vwap":376298.54,"rsi":62.5,"macd_hist":-3242.1},{"date":"2026-06-16","open":427000.0,"high":433000.0,"low":421500.0,"close":431000.0,"volume":251317.0,"ma5":394500.0,"ma20":379350.0,"ma60":293650.0,"bb_upper":467773.09,"bb_lower":290926.91,"vwap":381422.34,"rsi":63.6,"macd_hist":-1487.3},{"date":"2026-06-17","open":430000.0,"high":450000.0,"low":424000.0,"close":447000.0,"volume":343520.0,"ma5":410300.0,"ma20":386025.0,"ma60":297258.33,"bb_upper":473669.9,"bb_lower":298380.1,"vwap":386012.15,"rsi":65.8,"macd_hist":428.8},{"date":"2026-06-18","open":443000.0,"high":470500.0,"low":443000.0,"close":469000.0,"volume":558690.0,"ma5":431100.0,"ma20":393875.0,"ma60":301216.67,"bb_upper":481727.07,"bb_lower":306022.93,"vwap":393968.15,"rsi":68.5,"macd_hist":2727.6},{"date":"2026-06-19","open":481500.0,"high":516500.0,"low":478500.0,"close":497000.0,"volume":681949.0,"ma5":453400.0,"ma20":403125.0,"ma60":305875.0,"bb_upper":493597.95,"bb_lower":312652.05,"vwap":404562.53,"rsi":71.7,"macd_hist":5522.5},{"date":"2026-06-22","open":486500.0,"high":491500.0,"low":450500.0,"close":450500.0,"volume":539124.0,"ma5":458900.0,"ma20":407900.0,"ma60":309683.33,"bb_upper":497756.96,"bb_lower":318043.04,"vwap":409913.56,"rsi":60.8,"macd_hist":3714.7},{"date":"2026-06-23","open":455500.0,"high":503000.0,"low":425000.0,"close":425000.0,"volume":710092.0,"ma5":457700.0,"ma20":410925.0,"ma60":312975.0,"bb_upper":498679.01,"bb_lower":323170.99,"vwap":414455.76,"rsi":55.8,"macd_hist":448.5},{"date":"2026-06-24","open":435500.0,"high":443000.0,"low":415500.0,"close":433000.0,"volume":708886.0,"ma5":454900.0,"ma20":415175.0,"ma60":316491.67,"bb_upper":498203.39,"bb_lower":332146.61,"vwap":417950.76,"rsi":57.0,"macd_hist":-1423.6},{"date":"2026-06-25","open":446500.0,"high":467500.0,"low":441000.0,"close":447000.0,"volume":575517.0,"ma5":450500.0,"ma20":419800.0,"ma60":320225.0,"bb_upper":498805.26,"bb_lower":340794.74,"vwap":421920.33,"rsi":59.1,"macd_hist":-1937.7},{"date":"2026-06-26","open":450000.0,"high":450000.0,"low":415000.0,"close":432500.0,"volume":436390.0,"ma5":437600.0,"ma20":423550.0,"ma60":323775.0,"bb_upper":497031.04,"bb_lower":350068.96,"vwap":425253.31,"rsi":56.0,"macd_hist":-3388.1},{"date":"2026-06-29","open":420000.0,"high":420000.0,"low":400000.0,"close":408500.0,"volume":515300.0,"ma5":429200.0,"ma20":424550.0,"ma60":327075.0,"bb_upper":496552.12,"bb_lower":352547.88,"vwap":427894.79,"rsi":51.3,"macd_hist":-5947.8},{"date":"2026-06-30","open":408000.0,"high":416000.0,"low":385000.0,"close":401000.0,"volume":514927.0,"ma5":424400.0,"ma20":424100.0,"ma60":330008.33,"bb_upper":496595.81,"bb_lower":351604.19,"vwap":428046.73,"rsi":49.9,"macd_hist":-8002.0},{"date":"2026-07-01","open":407000.0,"high":409000.0,"low":375500.0,"close":387000.0,"volume":468913.0,"ma5":415200.0,"ma20":419450.0,"ma60":332841.67,"bb_upper":488706.88,"bb_lower":350193.12,"vwap":424090.35,"rsi":47.3,"macd_hist":-10028.4},{"date":"2026-07-02","open":371500.0,"high":381000.0,"low":352500.0,"close":370500.0,"volume":476440.0,"ma5":399900.0,"ma20":416075.0,"ma60":335333.33,"bb_upper":488051.07,"bb_lower":344098.93,"vwap":420036.59,"rsi":44.4,"macd_hist":-12067.7},{"date":"2026-07-03","open":368500.0,"high":389000.0,"low":355000.0,"close":383000.0,"volume":465820.0,"ma5":390000.0,"ma20":414600.0,"ma60":337950.0,"bb_upper":488077.96,"bb_lower":341122.04,"vwap":418500.0,"rsi":47.1,"macd_hist":-12130.1},{"date":"2026-07-06","open":386500.0,"high":398500.0,"low":376500.0,"close":393500.0,"volume":271668.0,"ma5":387000.0,"ma20":415500.0,"ma60":340808.33,"bb_upper":487385.14,"bb_lower":343614.86,"vwap":420319.93,"rsi":49.3,"macd_hist":-11050.0},{"date":"2026-07-07","open":385500.0,"high":392500.0,"low":359500.0,"close":375000.0,"volume":349281.0,"ma5":381800.0,"ma20":414600.0,"ma60":343083.33,"bb_upper":488103.74,"bb_lower":341096.26,"vwap":420381.44,"rsi":45.6,"macd_hist":-11136.1},{"date":"2026-07-08","open":359000.0,"high":366000.0,"low":332000.0,"close":346000.0,"volume":554995.0,"ma5":373600.0,"ma20":413500.0,"ma60":345016.67,"bb_upper":490514.69,"bb_lower":336485.31,"vwap":416376.53,"rsi":40.6,"macd_hist":-12593.2},{"date":"2026-07-09","open":336000.0,"high":346000.0,"low":317500.0,"close":326000.0,"volume":770711.0,"ma5":364700.0,"ma20":411550.0,"ma60":346541.67,"bb_upper":495406.33,"bb_lower":327693.67,"vwap":414102.91,"rsi":37.5,"macd_hist":-14230.2},{"date":"2026-07-10","open":332500.0,"high":347000.0,"low":329000.0,"close":340500.0,"volume":814715.0,"ma5":356200.0,"ma20":409300.0,"ma60":348300.0,"bb_upper":498353.15,"bb_lower":320246.85,"vwap":409112.28,"rsi":41.0,"macd_hist":-13660.1},{"date":"2026-07-13","open":333000.0,"high":340500.0,"low":314500.0,"close":326000.0,"volume":415904.0,"ma5":342700.0,"ma20":404450.0,"ma60":349633.33,"bb_upper":500641.09,"bb_lower":308258.91,"vwap":405520.18,"rsi":38.7,"macd_hist":-13556.0},{"date":"2026-07-14","open":314500.0,"high":324500.0,"low":301000.0,"close":317000.0,"volume":581945.0,"ma5":331100.0,"ma20":398750.0,"ma60":350616.67,"bb_upper":501597.1,"bb_lower":295902.9,"vwap":400040.02,"rsi":37.3,"macd_hist":-13367.5},{"date":"2026-07-15","open":335500.0,"high":343500.0,"low":330500.0,"close":337500.0,"volume":515532.0,"ma5":329400.0,"ma20":393275.0,"ma60":351941.67,"bb_upper":496962.02,"bb_lower":289587.98,"vwap":395806.87,"rsi":42.4,"macd_hist":-11223.0},{"date":"2026-07-16","open":344000.0,"high":344000.0,"low":318250.0,"close":331000.0,"volume":361459.0,"ma5":330400.0,"ma20":386375.0,"ma60":353233.33,"bb_upper":487170.72,"bb_lower":285579.28,"vwap":390240.52,"rsi":41.3,"macd_hist":-9662.4},{"date":"2026-07-20","open":312500.0,"high":325500.0,"low":296500.0,"close":301500.0,"volume":567164.0,"ma5":322600.0,"ma20":376600.0,"ma60":354033.33,"bb_upper":469861.15,"bb_lower":283338.85,"vwap":378957.18,"rsi":36.4,"macd_hist":-9995.4},{"date":"2026-07-21","open":299500.0,"high":317000.0,"low":294500.0,"close":316000.0,"volume":638066.0,"ma5":320600.0,"ma20":369875.0,"ma60":355033.33,"bb_upper":460044.94,"bb_lower":279705.06,"vwap":370512.92,"rsi":40.1,"macd_hist":-8667.0},{"date":"2026-07-22","open":336000.0,"high":343000.0,"low":318000.0,"close":320000.0,"volume":345636.0,"ma5":321200.0,"ma20":364625.0,"ma60":356241.67,"bb_upper":453498.58,"bb_lower":275751.42,"vwap":363537.27,"rsi":41.2,"macd_hist":-7017.2}]